[
  {
    "userid": 1,
    "webid": 1,
    "priceone": "7.5",
    "pricetwo": "0",
    "keywordid": 713,
    "username": "qunzhikeji",
    "platformid": 1,
    "keywordname": "长沙SEO",
    "websiteurl": "www.zhiuseo.com",
    "rank": 2
  },
  {
    "userid": 1,
    "webid": 1,
    "priceone": "9",
    "pricetwo": "0",
    "keywordid": 2441,
    "username": "qunzhikeji",
    "platformid": 1,
    "keywordname": "长沙做网站",
    "websiteurl": "www.zhiuseo.com",
    "rank": 45
  },
  {
    "userid": 1,
    "webid": 1,
    "priceone": "7.5",
    "pricetwo": "0",
    "keywordid": 711,
    "username": "qunzhikeji",
    "platformid": 1,
    "keywordname": "长沙建站公司",
    "websiteurl": "www.zhiuseo.com",
    "rank": 26
  },
  {
    "userid": 1,
    "webid": 1,
    "priceone": "7.5",
    "pricetwo": "0",
    "keywordid": 2420,
    "username": "qunzhikeji",
    "platformid": 1,
    "keywordname": "长沙百度推广",
    "websiteurl": "www.zhiuseo.com",
    "rank": 3
  },
  {
    "userid": 1,
    "webid": 1,
    "priceone": "7.5",
    "pricetwo": "0",
    "keywordid": 718,
    "username": "qunzhikeji",
    "platformid": 1,
    "keywordname": "长沙竞价托管",
    "websiteurl": "www.zhiuseo.com",
    "rank": 27
  },
  {
    "userid": 1,
    "webid": 1,
    "priceone": "7.5",
    "pricetwo": "0",
    "keywordid": 2427,
    "username": "qunzhikeji",
    "platformid": 1,
    "keywordname": "长沙网站SEO",
    "websiteurl": "www.zhiuseo.com",
    "rank": 8
  },
  {
    "userid": 1,
    "webid": 1,
    "priceone": "0",
    "pricetwo": "0",
    "keywordid": 715,
    "username": "qunzhikeji",
    "platformid": 1,
    "keywordname": "长沙网站优化",
    "websiteurl": "www.zhiuseo.com",
    "rank": 4
  },
  {
    "userid": 1,
    "webid": 1,
    "priceone": "7.5",
    "pricetwo": "0",
    "keywordid": 712,
    "username": "qunzhikeji",
    "platformid": 1,
    "keywordname": "长沙网站制作",
    "websiteurl": "www.zhiuseo.com",
    "rank": 100
  }
]